nnsplit-0.5.9_post0.dist-info/METADATA
nnsplit-0.5.9_post0.dist-info/WHEEL
nnsplit.cp38-win_amd64.pyd
nnsplit-0.5.9_post0.dist-info/RECORD
