Metadata-Version: 2.1
Name: nnsplit
Version: 0.5.9-post0
Requires-Dist: onnxruntime==1.12
Requires-Dist: tqdm>=4
Author: Benjamin Minixhofer <bminixhofer@gmail.com>
Author-Email: Benjamin Minixhofer <bminixhofer@gmail.com>
